{"Old Man": {"Info": {"Name": "Old Man", "Description": "Al old man and his music"}, "Start": {"Template": "800x200R", "BackGround": "", "Face": "", "Text": "All that is around is this old man.", "Border": "", "TextBorder": "", "FaceBorder": "", "Choices": {"Next": {"Reward": null, "Requirement": null, "Price": null, "Destination": "10", "Color": "green", "Command": null}}}, "10": {"Template": "800x200R", "BackGround": "", "Face": "SadDruid", "Text": "You must be here for the demo. Alright, here it is.", "Border": "", "TextBorder": "", "FaceBorder": "", "Choices": {"Play Song": {"Reward": "", "Requirement": "", "Price": "", "Destination": "PlaySong", "Color": "green", "Command": "PlaySong"}}}, "PlaySong": {"Template": "800x200FT", "BackGround": "", "Face": "", "Text": "He pulls out an old harmonica and plays\na somber tune. ", "Border": "", "TextBorder": "", "FaceBorder": "", "Choices": {"End Conversation": {"Reward": "", "Requirement": "", "Price": "", "Destination": "", "Color": "green", "Command": ""}}}}}